LICENSE.md
README.md
lookout_style-0.2.0-py3.5-nspkg.pth
requirements.txt
lookout/style/__init__.py
lookout/style/cloner.py
lookout/style/common.py
lookout/style/reporter.py
lookout/style/format/__init__.py
lookout/style/format/__main__.py
lookout/style/format/analyzer.py
lookout/style/format/classes.py
lookout/style/format/cmdline_tools.py
lookout/style/format/code_generator.py
lookout/style/format/config.py
lookout/style/format/descriptions.py
lookout/style/format/feature_extractor.py
lookout/style/format/features.py
lookout/style/format/model.py
lookout/style/format/optimizer.py
lookout/style/format/rules.py
lookout/style/format/uast_stability_checker.py
lookout/style/format/utils.py
lookout/style/format/virtual_node.py
lookout/style/format/benchmarks/__init__.py
lookout/style/format/benchmarks/compare_quality_reports.py
lookout/style/format/benchmarks/evaluate_smoke.py
lookout/style/format/benchmarks/expected_vnodes_number.py
lookout/style/format/benchmarks/general_report.py
lookout/style/format/benchmarks/generate_smoke.py
lookout/style/format/benchmarks/quality_report.py
lookout/style/format/benchmarks/quality_report_noisy.py
lookout/style/format/benchmarks/time_profile.py
lookout/style/format/benchmarks/data/js_smoke_init.tar.xz
lookout/style/format/benchmarks/data/quality_report_repos.csv
lookout/style/format/langs/__init__.py
lookout/style/format/langs/__main__.py
lookout/style/format/langs/roles.py.jinja2
lookout/style/format/langs/tokens.py.jinja2
lookout/style/format/langs/javascript/__init__.py
lookout/style/format/langs/javascript/roles.py
lookout/style/format/langs/javascript/token_unwrappers.py
lookout/style/format/langs/javascript/tokens.py
lookout/style/format/langs/javascript/uast_fixers.py
lookout/style/format/templates/comment.jinja2
lookout/style/format/templates/model_report.md.jinja2
lookout/style/format/templates/noisy_quality_report.md.jinja2
lookout/style/format/templates/quality_report.md.jinja2
lookout_style-0.2.0.dist-info/LICENSE.md
lookout_style-0.2.0.dist-info/METADATA
lookout_style-0.2.0.dist-info/WHEEL
lookout_style-0.2.0.dist-info/namespace_packages.txt
lookout_style-0.2.0.dist-info/top_level.txt
lookout_style-0.2.0.dist-info/RECORD
