Metadata-Version: 2.1
Name: lookout-style
Version: 0.2.0
Summary: Machine learning-based assisted code review - code style analyzers.
Home-page: https://github.com/src-d/style-analyzer
Author: source{d}
Author-email: machine-learning@sourced.tech
License: AGPL-3.0
Download-URL: https://github.com/src-d/style-analyzer
Keywords: machine learning on source code,babelfish,lookout
Platform: UNKNOWN
Classifier: Development Status :: 3 - Alpha
Classifier: Environment :: Console
Classifier: Intended Audience :: Developers
Classifier: License :: OSI Approved :: GNU Affero General Public License v3
Classifier: Operating System :: POSIX
Classifier: Programming Language :: Python :: 3.5
Classifier: Programming Language :: Python :: 3.6
Classifier: Programming Language :: Python :: 3.7
Classifier: Topic :: Software Development :: Quality Assurance
Requires-Dist: sourced-ml (<0.9,>=0.8.2)
Requires-Dist: lookout-sdk-ml (<0.20,>=0.19.0)
Requires-Dist: scikit-learn (<2.0,>=0.20)
Requires-Dist: scikit-optimize (<2.0,>=0.5)
Requires-Dist: pandas (<2.0,>=0.22)
Requires-Dist: gensim (<3.7.2,>=3.7.1)
Requires-Dist: google-compute-engine (<3.0,>=2.8.3)
Requires-Dist: xgboost (<2.0,>=0.72)
Requires-Dist: tabulate (<2.0,>=0.8.0)
Requires-Dist: python-igraph (<2.0,>=0.7.0)
Requires-Dist: smart-open (<2.0,>=1.8.1)
Requires-Dist: joblib (<1.0,>=0.13.2)
Provides-Extra: all_cpu
Requires-Dist: docker (<4.0,>=3.4.0) ; extra == 'all_cpu'
Requires-Dist: tensorflow (<2.0,>=1.0) ; extra == 'all_cpu'
Requires-Dist: matplotlib (<3.0,>=2.0) ; extra == 'all_cpu'
Requires-Dist: Flask (<2.0,>=1.0.0) ; extra == 'all_cpu'
Requires-Dist: Flask-Cors (<4.0,>=3.0.0) ; extra == 'all_cpu'
Provides-Extra: all_gpu
Requires-Dist: docker (<4.0,>=3.4.0) ; extra == 'all_gpu'
Requires-Dist: tensorflow-gpu (<2.0,>=1.0) ; extra == 'all_gpu'
Requires-Dist: matplotlib (<3.0,>=2.0) ; extra == 'all_gpu'
Requires-Dist: Flask (<2.0,>=1.0.0) ; extra == 'all_gpu'
Requires-Dist: Flask-Cors (<4.0,>=3.0.0) ; extra == 'all_gpu'
Provides-Extra: plot
Requires-Dist: matplotlib (<3.0,>=2.0) ; extra == 'plot'
Provides-Extra: test
Requires-Dist: docker (<4.0,>=3.4.0) ; extra == 'test'
Provides-Extra: tf
Requires-Dist: tensorflow (<2.0,>=1.0) ; extra == 'tf'
Provides-Extra: tf_gpu
Requires-Dist: tensorflow-gpu (<2.0,>=1.0) ; extra == 'tf_gpu'
Provides-Extra: web
Requires-Dist: Flask (<2.0,>=1.0.0) ; extra == 'web'
Requires-Dist: Flask-Cors (<4.0,>=3.0.0) ; extra == 'web'
